libwootility/cli.py
libwootility/device_linux.py
libwootility/helper.py
libwootility/hidraw.py
libwootility/libwootility_feature.py
libwootility/libwootility_report.proto
libwootility/libwootility_report.py
libwootility/libwootility_report_pb2.py
libwootility-1.0.1.dist-info/METADATA
libwootility-1.0.1.dist-info/WHEEL
libwootility-1.0.1.dist-info/entry_points.txt
libwootility-1.0.1.dist-info/RECORD
